{
  "id": "33cc63ab-1d9e-4310-b369-c12dda2d0145",
  "prevId": "4649108b-bc9c-4398-9d21-f4e1ff4d1e7f",
  "version": "7",
  "dialect": "postgresql",
  "tables": {
    "public.applications": {
      "name": "applications",
      "schema": "",
      "columns": {
        "id": {
          "name": "id",
          "type": "serial",
          "primaryKey": true,
          "notNull": true
        },
        "job_id": {
          "name": "job_id",
          "type": "integer",
          "primaryKey": false,
          "notNull": true
        },
        "name": {
          "name": "name",
          "type": "varchar(255)",
          "primaryKey": false,
          "notNull": true
        },
        "email": {
          "name": "email",
          "type": "varchar(255)",
          "primaryKey": false,
          "notNull": true
        },
        "resume": {
          "name": "resume",
          "type": "text",
          "primaryKey": false,
          "notNull": true
        },
        "cover_letter": {
          "name": "cover_letter",
          "type": "text",
          "primaryKey": false,
          "notNull": false
        },
        "created_at": {
          "name": "created_at",
          "type": "timestamp",
          "primaryKey": false,
          "notNull": true,
          "default": "now()"
        },
        "updated_at": {
          "name": "updated_at",
          "type": "timestamp",
          "primaryKey": false,
          "notNull": true,
          "default": "now()"
        }
      },
      "indexes": {},
      "foreignKeys": {
        "applications_job_id_jobs_id_fk": {
          "name": "applications_job_id_jobs_id_fk",
          "tableFrom": "applications",
          "tableTo": "jobs",
          "columnsFrom": [
            "job_id"
          ],
          "columnsTo": [
            "id"
          ],
          "onDelete": "cascade",
          "onUpdate": "no action"
        }
      },
      "compositePrimaryKeys": {},
      "uniqueConstraints": {},
      "policies": {},
      "checkConstraints": {},
      "isRLSEnabled": false
    },
    "public.jobs": {
      "name": "jobs",
      "schema": "",
      "columns": {
        "id": {
          "name": "id",
          "type": "serial",
          "primaryKey": true,
          "notNull": true
        },
        "title": {
          "name": "title",
          "type": "varchar(255)",
          "primaryKey": false,
          "notNull": true
        },
        "description": {
          "name": "description",
          "type": "text",
          "primaryKey": false,
          "notNull": true
        },
        "company": {
          "name": "company",
          "type": "varchar(255)",
          "primaryKey": false,
          "notNull": true
        },
        "location": {
          "name": "location",
          "type": "varchar(255)",
          "primaryKey": false,
          "notNull": true
        },
        "category": {
          "name": "category",
          "type": "category",
          "typeSchema": "public",
          "primaryKey": false,
          "notNull": true
        },
        "positions": {
          "name": "positions",
          "type": "integer",
          "primaryKey": false,
          "notNull": true,
          "default": 1
        },
        "created_at": {
          "name": "created_at",
          "type": "timestamp",
          "primaryKey": false,
          "notNull": true,
          "default": "now()"
        },
        "updated_at": {
          "name": "updated_at",
          "type": "timestamp",
          "primaryKey": false,
          "notNull": true,
          "default": "now()"
        }
      },
      "indexes": {},
      "foreignKeys": {},
      "compositePrimaryKeys": {},
      "uniqueConstraints": {},
      "policies": {},
      "checkConstraints": {},
      "isRLSEnabled": false
    }
  },
  "enums": {
    "public.category": {
      "name": "category",
      "schema": "public",
      "values": [
        "Software Developer",
        "QA Engineer",
        "Data Scientist",
        "UX Designer",
        "Frontend Developer",
        "Backend Developer",
        "Full Stack Developer",
        "Devops Engineer",
        "Junior Developer",
        "Entry Level Developer",
        "Junior QA",
        "QA Engineer",
        "QA Manager",
        "QA Analyst",
        "QA Tester"
      ]
    }
  },
  "schemas": {},
  "sequences": {},
  "roles": {},
  "policies": {},
  "views": {},
  "_meta": {
    "columns": {},
    "schemas": {},
    "tables": {}
  }
}